{
  "timestamp": "2025-03-05T00:31:16.235Z",
  "environment": {
    "node": "v23.9.0",
    "platform": "darwin",
    "arch": "arm64",
    "cpus": 8
  },
  "tests": {
    "create_small": {
      "durationMs": 0.753208,
      "memoryDelta": {
        "rss": 0.046875,
        "heapTotal": 0,
        "heapUsed": 0.20135498046875
      }
    },
    "create_medium": {
      "durationMs": 4.227709,
      "memoryDelta": {
        "rss": 0.0625,
        "heapTotal": 0.5,
        "heapUsed": 1.7133636474609375
      }
    },
    "create_large": {
      "durationMs": 17.660375,
      "memoryDelta": {
        "rss": 3.703125,
        "heapTotal": 4,
        "heapUsed": -3.4488525390625
      }
    },
    "find_by_type_small": {
      "durationMs": 0.161,
      "memoryDelta": {
        "rss": 0,
        "heapTotal": 0,
        "heapUsed": 0.0183563232421875
      }
    },
    "find_by_attribute_small": {
      "durationMs": 0.04875,
      "memoryDelta": {
        "rss": 0,
        "heapTotal": 0,
        "heapUsed": 0.024139404296875
      }
    },
    "get_relationships_small": {
      "durationMs": 0.062584,
      "memoryDelta": {
        "rss": 0,
        "heapTotal": 0,
        "heapUsed": 0.00411224365234375
      }
    },
    "find_by_type_medium": {
      "durationMs": 0.076708,
      "memoryDelta": {
        "rss": 0,
        "heapTotal": 0,
        "heapUsed": 0.04708099365234375
      }
    },
    "find_by_attribute_medium": {
      "durationMs": 0.178709,
      "memoryDelta": {
        "rss": 0,
        "heapTotal": 0,
        "heapUsed": 0.21715545654296875
      }
    },
    "get_relationships_medium": {
      "durationMs": 0.011041,
      "memoryDelta": {
        "rss": 0,
        "heapTotal": 0,
        "heapUsed": 0.0020751953125
      }
    },
    "find_by_type_large": {
      "durationMs": 0.223917,
      "memoryDelta": {
        "rss": 0,
        "heapTotal": 0,
        "heapUsed": 0.20362091064453125
      }
    },
    "find_by_attribute_large": {
      "durationMs": 0.4505,
      "memoryDelta": {
        "rss": 0,
        "heapTotal": 0,
        "heapUsed": 0.8261337280273438
      }
    },
    "get_relationships_large": {
      "durationMs": 0.015875,
      "memoryDelta": {
        "rss": 0,
        "heapTotal": 0,
        "heapUsed": 0.00218963623046875
      }
    },
    "json_export_small": {
      "durationMs": 0.196375,
      "memoryDelta": {
        "rss": 0,
        "heapTotal": 0,
        "heapUsed": 0.10669708251953125
      }
    },
    "graphml_export_small": {
      "durationMs": 0.413417,
      "memoryDelta": {
        "rss": 0.015625,
        "heapTotal": 0,
        "heapUsed": 0.20330810546875
      }
    },
    "json_export_medium": {
      "durationMs": 0.675125,
      "memoryDelta": {
        "rss": 0.421875,
        "heapTotal": 0.34375,
        "heapUsed": 0.6874542236328125
      }
    },
    "graphml_export_medium": {
      "durationMs": 1.053791,
      "memoryDelta": {
        "rss": 0.015625,
        "heapTotal": 0,
        "heapUsed": 1.6910934448242188
      }
    },
    "json_export_large": {
      "durationMs": 4.565417,
      "memoryDelta": {
        "rss": 7.328125,
        "heapTotal": 5.296875,
        "heapUsed": -5.0653533935546875
      }
    },
    "graphml_export_large": {
      "durationMs": 3.969083,
      "memoryDelta": {
        "rss": 0,
        "heapTotal": 0,
        "heapUsed": 6.7612762451171875
      }
    },
    "full_blob_export_small": {
      "durationMs": 3.046292,
      "memoryDelta": {
        "rss": 2.59375,
        "heapTotal": 2.359375,
        "heapUsed": -10.820945739746094
      }
    },
    "compressed_full_blob_export_small": {
      "durationMs": 2.21875,
      "memoryDelta": {
        "rss": 0.15625,
        "heapTotal": 0,
        "heapUsed": 0.950927734375
      }
    },
    "full_blob_export_medium": {
      "durationMs": 10.398708,
      "memoryDelta": {
        "rss": 5.453125,
        "heapTotal": 1.484375,
        "heapUsed": 9.115570068359375
      }
    },
    "compressed_full_blob_export_medium": {
      "durationMs": 17.983667,
      "memoryDelta": {
        "rss": 4.78125,
        "heapTotal": 1.5,
        "heapUsed": -5.220787048339844
      }
    }
  }
}